workflow2executable/__init__.py
workflow2executable/cli.py
workflow2executable/invocations.py
workflow2executable/workflow2executable.py
workflow2executable/templates/click_template.py.j2
workflow2executable-0.1.1.dist-info/AUTHORS.rst
workflow2executable-0.1.1.dist-info/LICENSE
workflow2executable-0.1.1.dist-info/LICENSE.txt
workflow2executable-0.1.1.dist-info/METADATA
workflow2executable-0.1.1.dist-info/WHEEL
workflow2executable-0.1.1.dist-info/entry_points.txt
workflow2executable-0.1.1.dist-info/top_level.txt
workflow2executable-0.1.1.dist-info/RECORD
