Metadata-Version: 2.1
Name: workflow2executable
Version: 0.1.1
Summary: Turn Galaxy Workflows into standalone scripts.
Home-page: https://github.com/mvdbeek/workflow2executable
Author: Marius van den Beek
Author-email: m.vandenbeek@gmail.com
License: MIT license
Keywords: workflow2executable
Platform: UNKNOWN
Classifier: Development Status :: 2 - Pre-Alpha
Classifier: Intended Audience :: Developers
Classifier: License :: OSI Approved :: MIT License
Classifier: Natural Language :: English
Classifier: Programming Language :: Python :: 3.5
Classifier: Programming Language :: Python :: 3.6
Classifier: Programming Language :: Python :: 3.7
Requires-Dist: Click (>=6.0)
Requires-Dist: bioblend (>=0.14.0)
Requires-Dist: jinja2
